{"basics":{"name":"Jack H. Culbert","label":"Researcher","image":"","email":"jack.culbert@gesis.org","url":"https://culbert.eu","summary":"PhD Student focusing on AI detection in Science","location":{"address":"6-8 Unter Sachsenhausen","postalCode":"50667","city":"Cologne","countryCode":"DE","region":"Germany"},"profiles":[{"network":"BlueSky","username":"jculbert.bsky.social","url":"https://bsky.app/profile/jculbert.bsky.social"}]},"work":[{"name":"GESIS - Leibniz Institute for the Social Sciences","position":"Researcher","url":"https://www.gesis.org/en/institute/about-us/staff/person/John.Culbert","startDate":"2023-04","endDate":"","summary":"","highlights":[""]},{"name":"Roke Manor Research","position":"Senior AI & ML Engineer","startDate":"2019-01","endDate":"2023-03","summary":""},{"name":"Arca Blanca","position":"Data Scientist","url":"https://www.linkedin.com/company/arcablanca","startDate":"2018-10","endDate":"2019-09","summary":""}],"education":[{"institution":"University of Nottingham","location":"Nottingham, United Kingdom","url":"https://https://www.nottingham.ac.uk/","area":"Mathematics","studyType":"Integrated Masters and Bachelors","startDate":"2014-09","endDate":"2018-07","courses":["Algebraic Topology, Scientific Computation, Graph Theory, Statistics"]}],"skills":[{"name":"Mathematics","level":"Master","icon":"fa-solid fa-hashtag","keywords":["Algebra","Computing","Statistics","Topology","Graph Theory"]}],"languages":[{"language":"English","fluency":"Native Speaker","icon":""},{"language":"German","fluency":"B2","icon":""}],"interests":[{"name":"Scientometrics","icon":"fa-solid fa-tag","keywords":["Author Name Disambiguation","Large Scale Analyses","Reproducible Science","Creativity in Science","Fraud Detection"]},{"name":"Computer Science","icon":"fa-solid fa-tag","keywords":["AI Detection in Science","Scholarly Document Processing - Extraction","Scientific Knowledge Graphs - Construction and Utilisation","Web Data Collection"]}],}